ytfetcher/__init__.py
ytfetcher/_cli.py
ytfetcher/_core.py
ytfetcher/_transcript_fetcher.py
ytfetcher/_youtube_dl.py
ytfetcher/config/__init__.py
ytfetcher/config/fetch_config.py
ytfetcher/config/http_config.py
ytfetcher/config/logging_config.py
ytfetcher/exceptions.py
ytfetcher/filters.py
ytfetcher/models/__init__.py
ytfetcher/models/channel.py
ytfetcher/py.typed
ytfetcher/services/__init__.py
ytfetcher/services/_preview.py
ytfetcher/services/exports.py
ytfetcher/utils/__init__.py
ytfetcher/utils/headers.py
ytfetcher/utils/log.py
ytfetcher/utils/state.py
ytfetcher-2.0.dist-info/entry_points.txt
ytfetcher-2.0.dist-info/LICENSE
ytfetcher-2.0.dist-info/METADATA
ytfetcher-2.0.dist-info/WHEEL
ytfetcher-2.0.dist-info/RECORD
