Metadata-Version: 2.3
Name: ytfetcher
Version: 2.0
Summary: YTFetcher lets you fetch YouTube transcripts in bulk with metadata like titles, publish dates, and thumbnails. Great for ML, NLP, and dataset generation.
License: MIT License
Keywords: yt,transcripts,youtube,cli,dataset,scraping,python,youtube-transcripts
Author: Ahmet Kaya
Author-email: kaya70875@gmail.com
Requires-Python: >=3.11,<3.14
Classifier: Programming Language :: Python :: 3
Classifier: License :: OSI Approved :: MIT License
Classifier: Operating System :: OS Independent
Classifier: Topic :: Software Development :: Libraries
Classifier: Topic :: Utilities
Requires-Dist: colorama (>=0.4.6,<0.5.0)
Requires-Dist: fake-useragent (>=2.2.0,<3.0.0)
Requires-Dist: httpx (>=0.28.1,<0.29.0)
Requires-Dist: mkdocs-material (>=9.7.1,<10.0.0)
Requires-Dist: pydantic (>=2.11.7,<3.0.0)
Requires-Dist: requests (>=2.32.4,<3.0.0)
Requires-Dist: rich (>=14.2.0,<15.0.0)
Requires-Dist: tqdm (>=4.67.1,<5.0.0)
Requires-Dist: types-requests (>=2.32.4.20250611,<3.0.0.0)
Requires-Dist: youtube-transcript-api (>=1.1.1,<2.0.0)
Requires-Dist: yt-dlp (>=2025.8.11,<2026.0.0)
Project-URL: Documentation, https://github.com/kaya70875/ytfetcher#readme
Project-URL: Homepage, https://github.com/kaya70875/ytfetcher
Project-URL: Repository, https://github.com/kaya70875/ytfetcher
